example/__init__.py
example/main.py
shigg/__init__.py
shigg/shigg.py
shigg/utils.py
shigg/default_drawing/__init__.py
shigg/default_drawing/pygame.py
shigg/elements/__init__.py
shigg/elements/_element.py
shigg/elements/_element_event.py
shigg/elements/button.py
shigg/elements/button_toggle.py
shigg/elements/draggable.py
shigg/elements/label.py
shigg/elements/left_right_selector.py
shigg/elements/move_and_resize_thumbs.py
shigg/elements/slider.py
shigg/elements/test.py
shigg/elements/vertical_slider.py
shigg-0.2.3.dist-info/LICENSE
shigg-0.2.3.dist-info/METADATA
shigg-0.2.3.dist-info/WHEEL
shigg-0.2.3.dist-info/top_level.txt
shigg-0.2.3.dist-info/RECORD
